examples/assignments.py
examples/contractor_policies.py
examples/contractors.py
examples/entities.py
examples/events.py
examples/insurance_application_sessions.py
examples/invoices.py
examples/job_categories.py
examples/jobs.py
examples/policies.py
examples/quotes.py
examples/webhooks.py
ten99policy/__init__.py
ten99policy/api_requestor.py
ten99policy/error.py
ten99policy/http_client.py
ten99policy/multipart_data_generator.py
ten99policy/object_classes.py
ten99policy/six.py
ten99policy/ten99policy_object.py
ten99policy/ten99policy_response.py
ten99policy/util.py
ten99policy/version.py
ten99policy/api_resources/__init__.py
ten99policy/api_resources/assignments.py
ten99policy/api_resources/contractor_policies.py
ten99policy/api_resources/contractors.py
ten99policy/api_resources/entities.py
ten99policy/api_resources/error_object.py
ten99policy/api_resources/events.py
ten99policy/api_resources/insurance_application_sessions.py
ten99policy/api_resources/invoices.py
ten99policy/api_resources/job_categories.py
ten99policy/api_resources/jobs.py
ten99policy/api_resources/list_object.py
ten99policy/api_resources/policies.py
ten99policy/api_resources/quotes.py
ten99policy/api_resources/webhooks.py
ten99policy/api_resources/abstract/__init__.py
ten99policy/api_resources/abstract/api_resource.py
ten99policy/api_resources/abstract/createable_api_resource.py
ten99policy/api_resources/abstract/custom_method.py
ten99policy/api_resources/abstract/deletable_api_resource.py
ten99policy/api_resources/abstract/listable_api_resource.py
ten99policy/api_resources/abstract/nested_resource_class_methods.py
ten99policy/api_resources/abstract/singleton_api_resource.py
ten99policy/api_resources/abstract/updateable_api_resource.py
ten99policy-1.1.8.dist-info/licenses/LICENSE
ten99policy-1.1.8.dist-info/METADATA
ten99policy-1.1.8.dist-info/WHEEL
ten99policy-1.1.8.dist-info/top_level.txt
ten99policy-1.1.8.dist-info/RECORD
