Metadata-Version: 2.4
Name: ten99policy
Version: 1.1.8
Summary: Python bindings for the ten99policy API
Home-page: https://github.com/1099policy/1099policy-client-python
Author: Ray Ventura
Author-email: Ray Ventura <support@1099policy.com>
License: The MIT License
Project-URL: Bug Tracker, https://github.com/1099policy/1099policy-client-python/issues
Project-URL: Documentation, https://1099policy.com/docs/api/?lang=python
Project-URL: Source Code, https://github.com/1099policy/1099policy-client-python
Keywords: ten99policy,api,insurance
Classifier: Development Status :: 5 - Production/Stable
Classifier: Intended Audience :: Developers
Classifier: License :: OSI Approved :: MIT License
Classifier: Operating System :: OS Independent
Classifier: Programming Language :: Python
Classifier: Programming Language :: Python :: 2
Classifier: Programming Language :: Python :: 2.7
Classifier: Programming Language :: Python :: 3
Classifier: Programming Language :: Python :: 3.4
Classifier: Programming Language :: Python :: 3.5
Classifier: Programming Language :: Python :: 3.6
Classifier: Programming Language :: Python :: 3.7
Classifier: Programming Language :: Python :: 3.8
Classifier: Programming Language :: Python :: 3.9
Classifier: Programming Language :: Python :: Implementation :: PyPy
Classifier: Topic :: Software Development :: Libraries :: Python Modules
Requires-Python: >=2.7, !=3.0.*, !=3.1.*, !=3.2.*, !=3.3.*
License-File: LICENSE
Requires-Dist: requests>=2.20; python_version >= "3.0"
Requires-Dist: requests[security]>=2.20; python_version < "3.0"
Dynamic: author
Dynamic: home-page
Dynamic: license-file
Dynamic: requires-python
